{"v":1,"region":"DNK","routes":{"DNK|ADAMOT":["DNK/shards/DNK-0001.json"],"DNK|AMAMOT":["DNK/shards/DNK-0001.json"],"DNK|ARHSMOT":["DNK/shards/DNK-0001.json"],"DNK|DJUMOT":["DNK/shards/DNK-0001.json"],"DNK|ESBMOT":["DNK/shards/DNK-0001.json"],"DNK|FHAVNMOT":["DNK/shards/DNK-0001.json"],"DNK|FSUNDMOT":["DNK/shards/DNK-0001.json"],"DNK|FYNMOT":["DNK/shards/DNK-0001.json"],"DNK|HELMOT":["DNK/shards/DNK-0001.json"],"DNK|HERMOT":["DNK/shards/DNK-0001.json"],"DNK|HILMOT":["DNK/shards/DNK-0001.json"],"DNK|HIRMOT":["DNK/shards/DNK-0001.json"],"DNK|HOLMOT":["DNK/shards/DNK-0001.json"],"DNK|HOLMOTHOL":["DNK/shards/DNK-0001.json"],"DNK|KALMOT":["DNK/shards/DNK-0001.json"],"DNK|KOGBUGMOT":["DNK/shards/DNK-0001.json"],"DNK|LYNMOT":["DNK/shards/DNK-0001.json"],"DNK|MESMOT":["DNK/shards/DNK-0001.json"],"DNK|MESMOTVES":["DNK/shards/DNK-0001.json"],"DNK|MIDMOT":["DNK/shards/DNK-0001.json"],"DNK|MOTRING3":["DNK/shards/DNK-0001.json"],"DNK|MOTRING4":["DNK/shards/DNK-0001.json"],"DNK|NORMOT":["DNK/shards/DNK-0001.json"],"DNK|OREMOT":["DNK/shards/DNK-0001.json"],"DNK|OSTMOT":["DNK/shards/DNK-0001.json"],"DNK|SONJYSMOT":["DNK/shards/DNK-0001.json"],"DNK|SONMOT":["DNK/shards/DNK-0001.json"],"DNK|SVEMOT":["DNK/shards/DNK-0001.json"],"DNK|SYDMOT":["DNK/shards/DNK-0001.json"],"DNK|TAUMOT":["DNK/shards/DNK-0001.json"],"DNK|VESTMOT":["DNK/shards/DNK-0001.json"],"DNK|MR":["DNK/shards/DNK-0001.json"],"DNK|MRAAL":["DNK/shards/DNK-0001.json"],"DNK|MRARO":["DNK/shards/DNK-0001.json"],"DNK|MRESB":["DNK/shards/DNK-0001.json"],"DNK|MRGLY":["DNK/shards/DNK-0001.json"],"DNK|MRHUR":["DNK/shards/DNK-0001.json"],"DNK|MRNYK":["DNK/shards/DNK-0001.json"],"DNK|MRODE":["DNK/shards/DNK-0001.json"],"DNK|MRSJA":["DNK/shards/DNK-0001.json"],"DNK|MRSVE":["DNK/shards/DNK-0001.json"],"DNK|MRVIB":["DNK/shards/DNK-0001.json"],"DNK|O2HIL":["DNK/shards/DNK-0001.json"],"DNK|O2KOB":["DNK/shards/DNK-0001.json"],"DNK|O3KOB":["DNK/shards/DNK-0001.json"],"DNK|O4KOB":["DNK/shards/DNK-0001.json"],"DNK|PR6":["DNK/shards/DNK-0001.json"],"DNK|PR8":["DNK/shards/DNK-0001.json"],"DNK|PR8FAA":["DNK/shards/DNK-0001.json"],"DNK|PR9":["DNK/shards/DNK-0001.json"],"DNK|PR9NYK":["DNK/shards/DNK-0001.json"],"DNK|PR11":["DNK/shards/DNK-0001.json"],"DNK|PR12":["DNK/shards/DNK-0001.json"],"DNK|PR13":["DNK/shards/DNK-0001.json"],"DNK|PR14":["DNK/shards/DNK-0001.json"],"DNK|PR15":["DNK/shards/DNK-0001.json"],"DNK|PR16":["DNK/shards/DNK-0001.json"],"DNK|PR16COP":["DNK/shards/DNK-0001.json"],"DNK|PR17":["DNK/shards/DNK-0001.json"],"DNK|PR18":["DNK/shards/DNK-0001.json"],"DNK|PR19":["DNK/shards/DNK-0001.json"],"DNK|PR21":["DNK/shards/DNK-0001.json"],"DNK|PR21RAN":["DNK/shards/DNK-0001.json"],"DNK|PR22":["DNK/shards/DNK-0001.json"],"DNK|PR23":["DNK/shards/DNK-0001.json"],"DNK|PR23JUE":["DNK/shards/DNK-0001.json"],"DNK|PR24":["DNK/shards/DNK-0001.json"],"DNK|PR25":["DNK/shards/DNK-0001.json"],"DNK|PR26":["DNK/shards/DNK-0001.json"],"DNK|PR28":["DNK/shards/DNK-0001.json"],"DNK|PR29":["DNK/shards/DNK-0001.json"],"DNK|PR30":["DNK/shards/DNK-0001.json"],"DNK|PR32":["DNK/shards/DNK-0001.json"],"DNK|PR34":["DNK/shards/DNK-0001.json"],"DNK|PR35":["DNK/shards/DNK-0001.json"],"DNK|PR38":["DNK/shards/DNK-0001.json"],"DNK|PR40":["DNK/shards/DNK-0001.json"],"DNK|PR41":["DNK/shards/DNK-0001.json"],"DNK|PR42":["DNK/shards/DNK-0001.json"],"DNK|PR43":["DNK/shards/DNK-0001.json"],"DNK|PR44":["DNK/shards/DNK-0001.json"],"DNK|PR46":["DNK/shards/DNK-0001.json"],"DNK|PR47":["DNK/shards/DNK-0001.json"],"DNK|PR52":["DNK/shards/DNK-0001.json"],"DNK|PR53":["DNK/shards/DNK-0001.json"],"DNK|PR54":["DNK/shards/DNK-0001.json"],"DNK|PR55":["DNK/shards/DNK-0001.json"],"DNK|PR57":["DNK/shards/DNK-0001.json"],"DNK|PR59":["DNK/shards/DNK-0001.json"],"DNK|O1AAL":["DNK/shards/DNK-0001.json"],"DNK|O1AAR":["DNK/shards/DNK-0001.json"],"DNK|O1BIL":["DNK/shards/DNK-0001.json"],"DNK|O1BRO":["DNK/shards/DNK-0001.json"],"DNK|O1HEL":["DNK/shards/DNK-0001.json"],"DNK|O1HOR":["DNK/shards/DNK-0001.json"],"DNK|O1ODE":["DNK/shards/DNK-0001.json"],"DNK|O1RAN":["DNK/shards/DNK-0001.json"],"DNK|O1ROS":["DNK/shards/DNK-0001.json"],"DNK|O1VEJ":["DNK/shards/DNK-0001.json"],"DNK|O2AAR":["DNK/shards/DNK-0001.json"],"DNK|O2BRO":["DNK/shards/DNK-0001.json"],"DNK|O2HEL":["DNK/shards/DNK-0001.json"],"DNK|O2HOL":["DNK/shards/DNK-0001.json"],"DNK|O2NAS":["DNK/shards/DNK-0001.json"],"DNK|O2ODE":["DNK/shards/DNK-0001.json"],"DNK|O2ROS":["DNK/shards/DNK-0001.json"],"DNK|O2VEJ":["DNK/shards/DNK-0001.json"],"DNK|O3AAR":["DNK/shards/DNK-0001.json"],"DNK|O3HEL":["DNK/shards/DNK-0001.json"],"DNK|O3ODE":["DNK/shards/DNK-0001.json"],"DNK|OFRE":["DNK/shards/DNK-0001.json"],"DNK|OGRE":["DNK/shards/DNK-0001.json"],"DNK|OHAD":["DNK/shards/DNK-0001.json"],"DNK|OHER":["DNK/shards/DNK-0001.json"],"DNK|OHJO":["DNK/shards/DNK-0001.json"],"DNK|OHOL":["DNK/shards/DNK-0001.json"],"DNK|OKOL":["DNK/shards/DNK-0001.json"],"DNK|ONAS":["DNK/shards/DNK-0001.json"],"DNK|ONSKA":["DNK/shards/DNK-0001.json"],"DNK|ONYK":["DNK/shards/DNK-0001.json"],"DNK|OSAB":["DNK/shards/DNK-0001.json"],"DNK|OSKI":["DNK/shards/DNK-0001.json"],"DNK|OTHI":["DNK/shards/DNK-0001.json"],"DNK|OVIB":["DNK/shards/DNK-0001.json"],"DNK|OVOR":["DNK/shards/DNK-0001.json"],"DNK|SR150":["DNK/shards/DNK-0001.json"],"DNK|SR151":["DNK/shards/DNK-0001.json"],"DNK|SR152":["DNK/shards/DNK-0001.json"],"DNK|SR153":["DNK/shards/DNK-0001.json"],"DNK|SR154":["DNK/shards/DNK-0001.json"],"DNK|SR155":["DNK/shards/DNK-0001.json"],"DNK|SR156":["DNK/shards/DNK-0001.json"],"DNK|SR157":["DNK/shards/DNK-0001.json"],"DNK|SR158":["DNK/shards/DNK-0001.json"],"DNK|SR159":["DNK/shards/DNK-0001.json"],"DNK|SR160":["DNK/shards/DNK-0001.json"],"DNK|SR161":["DNK/shards/DNK-0001.json"],"DNK|SR162":["DNK/shards/DNK-0001.json"],"DNK|SR163":["DNK/shards/DNK-0001.json"],"DNK|SR165":["DNK/shards/DNK-0001.json"],"DNK|SR167":["DNK/shards/DNK-0001.json"],"DNK|SR168":["DNK/shards/DNK-0001.json"],"DNK|SR170":["DNK/shards/DNK-0001.json"],"DNK|SR171":["DNK/shards/DNK-0001.json"],"DNK|SR175":["DNK/shards/DNK-0001.json"],"DNK|SR176":["DNK/shards/DNK-0001.json"],"DNK|SR179":["DNK/shards/DNK-0001.json"],"DNK|SR180":["DNK/shards/DNK-0001.json"],"DNK|SR181":["DNK/shards/DNK-0001.json"],"DNK|SR181HAN":["DNK/shards/DNK-0001.json"],"DNK|SR184":["DNK/shards/DNK-0001.json"],"DNK|SR184HOL":["DNK/shards/DNK-0001.json"],"DNK|SR185":["DNK/shards/DNK-0001.json"],"DNK|SR186":["DNK/shards/DNK-0001.json"],"DNK|SR187":["DNK/shards/DNK-0001.json"],"DNK|SR189":["DNK/shards/DNK-0001.json"],"DNK|SR190":["DNK/shards/DNK-0001.json"],"DNK|SR191":["DNK/shards/DNK-0001.json"],"DNK|SR195":["DNK/shards/DNK-0001.json"],"DNK|SR201":["DNK/shards/DNK-0001.json"],"DNK|SR203":["DNK/shards/DNK-0001.json"],"DNK|SR205":["DNK/shards/DNK-0001.json"],"DNK|SR207":["DNK/shards/DNK-0001.json"],"DNK|SR207LYN":["DNK/shards/DNK-0001.json"],"DNK|SR209":["DNK/shards/DNK-0001.json"],"DNK|SR211":["DNK/shards/DNK-0001.json"],"DNK|SR213":["DNK/shards/DNK-0001.json"],"DNK|SR215":["DNK/shards/DNK-0001.json"],"DNK|SR217":["DNK/shards/DNK-0001.json"],"DNK|SR219":["DNK/shards/DNK-0001.json"],"DNK|SR221":["DNK/shards/DNK-0001.json"],"DNK|SR223":["DNK/shards/DNK-0001.json"],"DNK|SR225":["DNK/shards/DNK-0001.json"],"DNK|SR227":["DNK/shards/DNK-0001.json"],"DNK|SR229":["DNK/shards/DNK-0001.json"],"DNK|SR231":["DNK/shards/DNK-0001.json"],"DNK|SR233":["DNK/shards/DNK-0001.json"],"DNK|SR235":["DNK/shards/DNK-0001.json"],"DNK|SR237":["DNK/shards/DNK-0001.json"],"DNK|SR239":["DNK/shards/DNK-0001.json"],"DNK|SR243":["DNK/shards/DNK-0001.json"],"DNK|SR251":["DNK/shards/DNK-0001.json"],"DNK|SR255":["DNK/shards/DNK-0001.json"],"DNK|SR259":["DNK/shards/DNK-0001.json"],"DNK|SR261":["DNK/shards/DNK-0001.json"],"DNK|SR263":["DNK/shards/DNK-0001.json"],"DNK|SR265":["DNK/shards/DNK-0001.json"],"DNK|SR267":["DNK/shards/DNK-0001.json"],"DNK|SR269":["DNK/shards/DNK-0001.json"],"DNK|SR271":["DNK/shards/DNK-0001.json"],"DNK|SR275":["DNK/shards/DNK-0001.json"],"DNK|SR277":["DNK/shards/DNK-0001.json"],"DNK|SR283":["DNK/shards/DNK-0001.json"],"DNK|SR287":["DNK/shards/DNK-0001.json"],"DNK|SR289":["DNK/shards/DNK-0001.json"],"DNK|SR291":["DNK/shards/DNK-0001.json"],"DNK|SR293":["DNK/shards/DNK-0001.json"],"DNK|SR297":["DNK/shards/DNK-0001.json"],"DNK|SR301":["DNK/shards/DNK-0001.json"],"DNK|SR303":["DNK/shards/DNK-0001.json"],"DNK|SR305":["DNK/shards/DNK-0002.json"],"DNK|SR307":["DNK/shards/DNK-0002.json"],"DNK|SR311":["DNK/shards/DNK-0002.json"],"DNK|SR313":["DNK/shards/DNK-0002.json"],"DNK|SR315":["DNK/shards/DNK-0002.json"],"DNK|SR317":["DNK/shards/DNK-0002.json"],"DNK|SR323":["DNK/shards/DNK-0002.json"],"DNK|SR327":["DNK/shards/DNK-0002.json"],"DNK|SR329":["DNK/shards/DNK-0002.json"],"DNK|SR335":["DNK/shards/DNK-0002.json"],"DNK|SR401":["DNK/shards/DNK-0002.json"],"DNK|SR403":["DNK/shards/DNK-0002.json"],"DNK|SR405":["DNK/shards/DNK-0002.json"],"DNK|SR409":["DNK/shards/DNK-0002.json"],"DNK|SR411":["DNK/shards/DNK-0002.json"],"DNK|SR417":["DNK/shards/DNK-0002.json"],"DNK|SR419":["DNK/shards/DNK-0002.json"],"DNK|SR423":["DNK/shards/DNK-0002.json"],"DNK|SR425":["DNK/shards/DNK-0002.json"],"DNK|SR427":["DNK/shards/DNK-0002.json"],"DNK|SR429":["DNK/shards/DNK-0002.json"],"DNK|SR431":["DNK/shards/DNK-0002.json"],"DNK|SR433":["DNK/shards/DNK-0002.json"],"DNK|SR435":["DNK/shards/DNK-0002.json"],"DNK|SR437":["DNK/shards/DNK-0002.json"],"DNK|SR439":["DNK/shards/DNK-0002.json"],"DNK|SR442":["DNK/shards/DNK-0002.json"],"DNK|SR443":["DNK/shards/DNK-0002.json"],"DNK|SR445":["DNK/shards/DNK-0002.json"],"DNK|SR447":["DNK/shards/DNK-0002.json"],"DNK|SR449":["DNK/shards/DNK-0002.json"],"DNK|SR451":["DNK/shards/DNK-0002.json"],"DNK|SR453":["DNK/shards/DNK-0002.json"],"DNK|SR455":["DNK/shards/DNK-0002.json"],"DNK|SR457":["DNK/shards/DNK-0002.json"],"DNK|SR459":["DNK/shards/DNK-0002.json"],"DNK|SR461":["DNK/shards/DNK-0002.json"],"DNK|SR463":["DNK/shards/DNK-0002.json"],"DNK|SR465":["DNK/shards/DNK-0002.json"],"DNK|SR467":["DNK/shards/DNK-0002.json"],"DNK|SR469":["DNK/shards/DNK-0002.json"],"DNK|SR471":["DNK/shards/DNK-0002.json"],"DNK|SR473":["DNK/shards/DNK-0002.json"],"DNK|SR475":["DNK/shards/DNK-0002.json"],"DNK|SR481":["DNK/shards/DNK-0002.json"],"DNK|SR487":["DNK/shards/DNK-0002.json"],"DNK|SR501":["DNK/shards/DNK-0002.json"],"DNK|SR502":["DNK/shards/DNK-0002.json"],"DNK|SR503":["DNK/shards/DNK-0002.json"],"DNK|SR505":["DNK/shards/DNK-0002.json"],"DNK|SR507":["DNK/shards/DNK-0002.json"],"DNK|SR509":["DNK/shards/DNK-0002.json"],"DNK|SR511":["DNK/shards/DNK-0002.json"],"DNK|SR513":["DNK/shards/DNK-0002.json"],"DNK|SR515":["DNK/shards/DNK-0002.json"],"DNK|SR517":["DNK/shards/DNK-0002.json"],"DNK|SR519":["DNK/shards/DNK-0002.json"],"DNK|SR521":["DNK/shards/DNK-0002.json"],"DNK|SR523":["DNK/shards/DNK-0002.json"],"DNK|SR525":["DNK/shards/DNK-0002.json"],"DNK|SR527":["DNK/shards/DNK-0002.json"],"DNK|SR531":["DNK/shards/DNK-0002.json"],"DNK|SR531UDB":["DNK/shards/DNK-0002.json"],"DNK|SR533":["DNK/shards/DNK-0002.json"],"DNK|SR535":["DNK/shards/DNK-0002.json"],"DNK|SR537":["DNK/shards/DNK-0002.json"],"DNK|SR539":["DNK/shards/DNK-0002.json"],"DNK|SR541":["DNK/shards/DNK-0002.json"],"DNK|SR541ASA":["DNK/shards/DNK-0002.json"],"DNK|SR543":["DNK/shards/DNK-0002.json"],"DNK|SR545":["DNK/shards/DNK-0002.json"],"DNK|SR545HUR":["DNK/shards/DNK-0002.json"],"DNK|SR547":["DNK/shards/DNK-0002.json"],"DNK|SR549":["DNK/shards/DNK-0002.json"],"DNK|SR551":["DNK/shards/DNK-0002.json"],"DNK|SR553":["DNK/shards/DNK-0002.json"],"DNK|SR555":["DNK/shards/DNK-0002.json"],"DNK|SR557":["DNK/shards/DNK-0002.json"],"DNK|SR559":["DNK/shards/DNK-0002.json"],"DNK|SR561":["DNK/shards/DNK-0002.json"],"DNK|SR563":["DNK/shards/DNK-0002.json"],"DNK|SR565":["DNK/shards/DNK-0002.json"],"DNK|SR567":["DNK/shards/DNK-0002.json"],"DNK|SR569":["DNK/shards/DNK-0002.json"],"DNK|SR571":["DNK/shards/DNK-0002.json"],"DNK|SR573":["DNK/shards/DNK-0002.json"],"DNK|SR575":["DNK/shards/DNK-0002.json"],"DNK|SR579":["DNK/shards/DNK-0002.json"],"DNK|SR581":["DNK/shards/DNK-0002.json"],"DNK|SR581AMT":["DNK/shards/DNK-0002.json"],"DNK|SR583":["DNK/shards/DNK-0002.json"],"DNK|SR585":["DNK/shards/DNK-0002.json"],"DNK|SR587":["DNK/shards/DNK-0002.json"],"DNK|SR589":["DNK/shards/DNK-0002.json"],"DNK|SR591":["DNK/shards/DNK-0002.json"],"DNK|SR593":["DNK/shards/DNK-0002.json"],"DNK|SR595":["DNK/shards/DNK-0002.json"],"DNK|SR597":["DNK/shards/DNK-0002.json"],"DNK|E20":["DNK/shards/DNK-0002.json"],"DNK|E39":["DNK/shards/DNK-0002.json"],"DNK|E45":["DNK/shards/DNK-0002.json"],"DNK|E47":["DNK/shards/DNK-0002.json"],"DNK|E55":["DNK/shards/DNK-0002.json"]}}