{"v":1,"region":"HI","routes":{"HI|HI11":["HI/usahi/hi.hi011.json"],"HI|HI19":["HI/usahi/hi.hi019.json"],"HI|HI30":["HI/usahi/hi.hi030.json"],"HI|HI31":["HI/usahi/hi.hi031.json"],"HI|HI32":["HI/usahi/hi.hi032.json"],"HI|HI32A":["HI/usahi/hi.hi032a.json"],"HI|HI36":["HI/usahi/hi.hi036.json"],"HI|HI36A":["HI/usahi/hi.hi036a.json"],"HI|HI37":["HI/usahi/hi.hi037.json"],"HI|HI50":["HI/usahi/hi.hi050.json"],"HI|HI51":["HI/usahi/hi.hi051.json"],"HI|HI56":["HI/usahi/hi.hi056.json"],"HI|HI58":["HI/usahi/hi.hi058.json"],"HI|HI61":["HI/usahi/hi.hi061.json"],"HI|HI63":["HI/usahi/hi.hi063.json"],"HI|HI64":["HI/usahi/hi.hi064.json"],"HI|HI65":["HI/usahi/hi.hi065.json"],"HI|HI72":["HI/usahi/hi.hi072.json"],"HI|HI76":["HI/usahi/hi.hi076.json"],"HI|HI78":["HI/usahi/hi.hi078.json"],"HI|HI80":["HI/usahi/hi.hi080.json"],"HI|HI83":["HI/usahi/hi.hi083.json"],"HI|HI92":["HI/usahi/hi.hi092.json"],"HI|HI93":["HI/usahi/hi.hi093.json"],"HI|HI98":["HI/usahi/hi.hi098.json"],"HI|HI99":["HI/usahi/hi.hi099.json"],"HI|HI130":["HI/usahi/hi.hi130.json"],"HI|HI139":["HI/usahi/hi.hi139.json"],"HI|HI190":["HI/usahi/hi.hi190.json"],"HI|HI200":["HI/usahi/hi.hi200.json"],"HI|HI2000":["HI/usahi/hi.hi2000.json"],"HI|HI220":["HI/usahi/hi.hi220.json"],"HI|HI250":["HI/usahi/hi.hi250.json"],"HI|HI270":["HI/usahi/hi.hi270.json"],"HI|HI3000":["HI/usahi/hi.hi3000.json"],"HI|HI310":["HI/usahi/hi.hi310.json"],"HI|HI311":["HI/usahi/hi.hi311.json"],"HI|HI340":["HI/usahi/hi.hi340.json"],"HI|HI3400":["HI/usahi/hi.hi3400.json"],"HI|HI3500":["HI/usahi/hi.hi3500.json"],"HI|HI360":["HI/usahi/hi.hi360.json"],"HI|HI377":["HI/usahi/hi.hi377.json"],"HI|HI378":["HI/usahi/hi.hi378.json"],"HI|HI380":["HI/usahi/hi.hi380.json"],"HI|HI3800":["HI/usahi/hi.hi3800.json"],"HI|HI440":["HI/usahi/hi.hi440.json"],"HI|HI450":["HI/usahi/hi.hi450.json"],"HI|HI460":["HI/usahi/hi.hi460.json"],"HI|HI470":["HI/usahi/hi.hi470.json"],"HI|HI480":["HI/usahi/hi.hi480.json"],"HI|HI540":["HI/usahi/hi.hi540.json"],"HI|HI541":["HI/usahi/hi.hi541.json"],"HI|HI550":["HI/usahi/hi.hi550.json"],"HI|HI560":["HI/usahi/hi.hi560.json"],"HI|HI570":["HI/usahi/hi.hi570.json"],"HI|HI580":["HI/usahi/hi.hi580.json"],"HI|HI583":["HI/usahi/hi.hi583.json"],"HI|HI7012":["HI/usahi/hi.hi7012.json"],"HI|HI7101":["HI/usahi/hi.hi7101.json"],"HI|HI7110":["HI/usahi/hi.hi7110.json"],"HI|HI7310":["HI/usahi/hi.hi7310.json"],"HI|HI750":["HI/usahi/hi.hi750.json"],"HI|HI8930":["HI/usahi/hi.hi8930.json"],"HI|HI930":["HI/usahi/hi.hi930.json"],"HI|IH1":["HI/usai/hi.ih001.json"],"HI|IH2":["HI/usai/hi.ih002.json"],"HI|IH3":["HI/usai/hi.ih003.json"],"HI|IH201":["HI/usai/hi.ih201.json"],"HI|CHACRARD":["HI/usanp/hi.chacrard.json"],"HI|CRARD":["HI/usanp/hi.crard.json"],"HI|CRARIMDR":["HI/usanp/hi.crarimdr.json"]}}