{"v":1,"region":"INDMH","routes":{"INDMH|AH43X":["INDMH/indaho/indmh.ah043x.json"],"INDMH|AH46X":["INDMH/indaho/indmh.ah046x.json"],"INDMH|AH47X":["INDMH/indaho/indmh.ah047x.json"],"INDMH|AH47XMUM":["INDMH/indaho/indmh.ah047xmum.json"],"INDMH|EASFWY":["INDMH/index/indmh.easfwy.json"],"INDMH|MPEXPY":["INDMH/index/indmh.mpexpy.json"],"INDMH|KA10":["INDMH/indka/indmh.ka010.json"],"INDMH|KA34":["INDMH/indka/indmh.ka034.json"],"INDMH|KA78SHI":["INDMH/indka/indmh.ka078shi.json"],"INDMH|KA78TER":["INDMH/indka/indmh.ka078ter.json"],"INDMH|KA122":["INDMH/indka/indmh.ka122.json"],"INDMH|KA124BHO":["INDMH/indka/indmh.ka124bho.json"],"INDMH|KA124DUD":["INDMH/indka/indmh.ka124dud.json"],"INDMH|KA124KAS":["INDMH/indka/indmh.ka124kas.json"],"INDMH|KA124KES":["INDMH/indka/indmh.ka124kes.json"],"INDMH|KA141GAN":["INDMH/indka/indmh.ka141gan.json"],"INDMH|MH116":["INDMH/indmh/indmh.mh116.json"],"INDMH|MH129":["INDMH/indmh/indmh.mh129.json"],"INDMH|MH129SHI":["INDMH/indmh/indmh.mh129shi.json"],"INDMH|MH135":["INDMH/indmh/indmh.mh135.json"],"INDMH|MH135HAN":["INDMH/indmh/indmh.mh135han.json"],"INDMH|MH137":["INDMH/indmh/indmh.mh137.json"],"INDMH|NH44AMA":["INDMH/indnh/indmh.nh044ama.json"],"INDMH|NH44ENAG":["INDMH/indnh/indmh.nh044enag.json"],"INDMH|NH44WNAG":["INDMH/indnh/indmh.nh044wnag.json"],"INDMH|NH48":["INDMH/indnh/indmh.nh048.json"],"INDMH|NH50":["INDMH/indnh/indmh.nh050.json"],"INDMH|NH52":["INDMH/indnh/indmh.nh052.json"],"INDMH|NH61":["INDMH/indnh/indmh.nh061.json"],"INDMH|NH63":["INDMH/indnh/indmh.nh063.json"],"INDMH|NH63DEG":["INDMH/indnh/indmh.nh063deg.json"],"INDMH|NH63SIR":["INDMH/indnh/indmh.nh063sir.json"],"INDMH|NH65":["INDMH/indnh/indmh.nh065.json"],"INDMH|NH66":["INDMH/indnh/indmh.nh066.json"],"INDMH|NH150":["INDMH/indnh/indmh.nh150.json"],"INDMH|NH160":["INDMH/indnh/indmh.nh160.json"],"INDMH|NH161":["INDMH/indnh/indmh.nh161.json"],"INDMH|NH161A":["INDMH/indnh/indmh.nh161a.json"],"INDMH|NH161AVAJ":["INDMH/indnh/indmh.nh161avaj.json"],"INDMH|NH161BBPOT":["INDMH/indnh/indmh.nh161bbpot.json"],"INDMH|NH161BBSAN":["INDMH/indnh/indmh.nh161bbsan.json"],"INDMH|NH161BBSIR":["INDMH/indnh/indmh.nh161bbsir.json"],"INDMH|NH161SAL":["INDMH/indnh/indmh.nh161sal.json"],"INDMH|NH166E":["INDMH/indnh/indmh.nh166e.json"],"INDMH|NH353B":["INDMH/indnh/indmh.nh353b.json"],"INDMH|NH353C":["INDMH/indnh/indmh.nh353c.json"],"INDMH|NH548B":["INDMH/indnh/indmh.nh548b.json"],"INDMH|NH548H":["INDMH/indnh/indmh.nh548h.json"],"INDMH|NH561A":["INDMH/indnh/indmh.nh561a.json"],"INDMH|NH561ATIK":["INDMH/indnh/indmh.nh561atik.json"],"INDMH|NH748AAMWS":["INDMH/indnh/indmh.nh748aamws.json"],"INDMH|NH748AAVAL":["INDMH/indnh/indmh.nh748aaval.json"],"INDMH|NH752K":["INDMH/indnh/indmh.nh752k.json"]}}