{"v":1,"region":"INDRJ","routes":{"INDRJ|AH43X":["INDRJ/indaho/indrj.ah043x.json"],"INDRJ|JAIELVRD":["INDRJ/index/indrj.jaielvrd.json"],"INDRJ|JKEXPY":["INDRJ/index/indrj.jkexpy.json"],"INDRJ|NH21":["INDRJ/indnh/indrj.nh021.json"],"INDRJ|NH27":["INDRJ/indnh/indrj.nh027.json"],"INDRJ|NH44":["INDRJ/indnh/indrj.nh044.json"],"INDRJ|NH48":["INDRJ/indnh/indrj.nh048.json"],"INDRJ|NH52":["INDRJ/indnh/indrj.nh052.json"],"INDRJ|NH123BHA":["INDRJ/indnh/indrj.nh123bha.json"],"INDRJ|NH123DHA":["INDRJ/indnh/indrj.nh123dha.json"],"INDRJ|NH123RUP":["INDRJ/indnh/indrj.nh123rup.json"],"INDRJ|NH552":["INDRJ/indnh/indrj.nh552.json"],"INDRJ|UP33":["INDRJ/indup/indrj.up033.json"]}}