{"v":1,"region":"MEXNAY","routes":{"MEXNAY|MEX15D":["MEXNAY/mexd/mexnay.mex015d.json"],"MEXNAY|MEX15DCHA":["MEXNAY/mexd/mexnay.mex015dcha.json"],"MEXNAY|MEX15DESC":["MEXNAY/mexd/mexnay.mex015desc.json"],"MEXNAY|MEX15DTEP":["MEXNAY/mexd/mexnay.mex015dtep.json"],"MEXNAY|MEX68D":["MEXNAY/mexd/mexnay.mex068d.json"],"MEXNAY|MEX70D":["MEXNAY/mexd/mexnay.mex070d.json"],"MEXNAY|MEX76D":["MEXNAY/mexd/mexnay.mex076d.json"],"MEXNAY|MEX200D":["MEXNAY/mexd/mexnay.mex200d.json"],"MEXNAY|MEX5":["MEXNAY/mexf/mexnay.mex005.json"],"MEXNAY|MEX9":["MEXNAY/mexf/mexnay.mex009.json"],"MEXNAY|MEX10":["MEXNAY/mexf/mexnay.mex010.json"],"MEXNAY|MEX11":["MEXNAY/mexf/mexnay.mex011.json"],"MEXNAY|MEX12":["MEXNAY/mexf/mexnay.mex012.json"],"MEXNAY|MEX15":["MEXNAY/mexf/mexnay.mex015.json"],"MEXNAY|MEX15AIT":["MEXNAY/mexf/mexnay.mex015ait.json"],"MEXNAY|MEX15CAM":["MEXNAY/mexf/mexnay.mex015cam.json"],"MEXNAY|MEX26":["MEXNAY/mexf/mexnay.mex026.json"],"MEXNAY|MEX27":["MEXNAY/mexf/mexnay.mex027.json"],"MEXNAY|MEX44":["MEXNAY/mexf/mexnay.mex044.json"],"MEXNAY|MEX68":["MEXNAY/mexf/mexnay.mex068.json"],"MEXNAY|MEX68PAJ":["MEXNAY/mexf/mexnay.mex068paj.json"],"MEXNAY|MEX68QUI":["MEXNAY/mexf/mexnay.mex068qui.json"],"MEXNAY|MEX72":["MEXNAY/mexf/mexnay.mex072.json"],"MEXNAY|MEX74":["MEXNAY/mexf/mexnay.mex074.json"],"MEXNAY|MEX76":["MEXNAY/mexf/mexnay.mex076.json"],"MEXNAY|MEX76IXT":["MEXNAY/mexf/mexnay.mex076ixt.json"],"MEXNAY|MEX78":["MEXNAY/mexf/mexnay.mex078.json"],"MEXNAY|MEX78PUE":["MEXNAY/mexf/mexnay.mex078pue.json"],"MEXNAY|MEX200":["MEXNAY/mexf/mexnay.mex200.json"],"MEXNAY|MEX200MIT":["MEXNAY/mexf/mexnay.mex200mit.json"]}}