{"v":1,"shard":{"region":"YEM","id":"0001"},"routes":[{"v":1,"src":"hwy_data/YEM/asimo/yem.m045.wpt","sys":"asimo","rg":"YEM","rt":"m045","pt":[[17.552063,43.457279],[13.610786,44.093285]],"lb":[["SAU/YEM"],["M100"]]},{"v":1,"src":"hwy_data/YEM/asimo/yem.m055.wpt","sys":"asimo","rg":"YEM","rt":"m055","pt":[[16.51082,42.972593],[13.321977,43.265362]],"lb":[["SAU/YEM"],["M100"]]},{"v":1,"src":"hwy_data/YEM/asimo/yem.m100.wpt","sys":"asimo","rg":"YEM","rt":"m100","pt":[[17.813254,52.5634],[13.610786,44.093285],[13.321977,43.265362]],"lb":[["OMN/YEM"],["M45"],["M55"]]}]}